{
  "destination-list": [
    {
      "thumbnail": "https://backpacktraveler.qodeinteractive.com/wp-content/uploads/2018/08/spain-single-2-2.jpg",
      "imgMap": "https://backpacktraveler.qodeinteractive.com/wp-content/uploads/2018/08/spain-img.png",
      "national": "spain",
      "categories": ["fishing", "overnight"],
      "createdAt": 1666554133234,
      "updatedAt": 1666554133234,
      "id": 1
    },
    {
      "thumbnail": "https://backpacktraveler.qodeinteractive.com/wp-content/uploads/2018/08/destination-australia-single2.jpg",
      "imgMap": "https://backpacktraveler.qodeinteractive.com/wp-content/uploads/2018/08/australia-map.png",
      "national": "australia",
      "categories": ["camping", "restaurants"],
      "createdAt": 1666560266016,
      "updatedAt": 1666560266016,
      "id": 2
    },
    {
      "thumbnail": "https://backpacktraveler.qodeinteractive.com/wp-content/uploads/2018/08/peru-destination.jpg",
      "imgMap": "https://backpacktraveler.qodeinteractive.com/wp-content/uploads/2018/08/peru-img.png",
      "national": "peru",
      "categories": ["low budget"],
      "createdAt": 1666560430339,
      "updatedAt": 1666560430339,
      "id": 3
    },
    {
      "thumbnail": "https://backpacktraveler.qodeinteractive.com/wp-content/uploads/2018/08/brazil-single-2-2.jpg",
      "imgMap": "https://backpacktraveler.qodeinteractive.com/wp-content/uploads/2018/08/brazil-img-1.png",
      "national": "brazil",
      "categories": ["beaches", "photography"],
      "createdAt": 1666560601997,
      "updatedAt": 1666560601997,
      "id": 4
    },
    {
      "thumbnail": "https://backpacktraveler.qodeinteractive.com/wp-content/uploads/2018/08/h2-destination-1-img-2-2.jpg",
      "imgMap": "https://backpacktraveler.qodeinteractive.com/wp-content/uploads/2018/08/uk-img.png",
      "national": "united kingdom",
      "categories": ["flights", "guides"],
      "createdAt": 1666560733674,
      "updatedAt": 1666560733674,
      "id": 5
    },
    {
      "thumbnail": "https://backpacktraveler.qodeinteractive.com/wp-content/uploads/2018/08/h2-destination-3-img-2.jpg",
      "imgMap": "https://backpacktraveler.qodeinteractive.com/wp-content/uploads/2018/08/italy-img.png",
      "national": "italy",
      "categories": ["flights", "shopping"],
      "createdAt": 1666560796293,
      "updatedAt": 1666560796293,
      "id": 6
    },
    {
      "thumbnail": "https://backpacktraveler.qodeinteractive.com/wp-content/uploads/2018/09/india-destination-3.jpg",
      "imgMap": "https://backpacktraveler.qodeinteractive.com/wp-content/uploads/2018/08/india-img-2.png",
      "national": "india",
      "categories": ["flights", "beaches"],
      "createdAt": 1666560942110,
      "updatedAt": 1666560942110,
      "id": 7
    },
    {
      "thumbnail": "https://backpacktraveler.qodeinteractive.com/wp-content/uploads/2018/09/greece-destination-2.jpg",
      "imgMap": "https://backpacktraveler.qodeinteractive.com/wp-content/uploads/2018/09/greek-map1-4.png",
      "national": "greece",
      "categories": ["flights", "guides"],
      "createdAt": 1666561006954,
      "updatedAt": 1666561006954,
      "id": 8
    },
    {
      "thumbnail": "https://backpacktraveler.qodeinteractive.com/wp-content/uploads/2018/09/paris-destination-img.jpg",
      "imgMap": "https://backpacktraveler.qodeinteractive.com/wp-content/uploads/2018/09/france-img-3.png",
      "national": "france",
      "categories": ["flights", "guides"],
      "createdAt": 1666561080305,
      "updatedAt": 1666561080305,
      "id": 9
    }
  ],

  "things-to-see": [
    {
      "idDestination": 1,
      "id": "3906dd08-f27c-48ca-9b88-d50d2bfe037a",
      "national": "spain",
      "title": "welcome to spain travel guide",
      "description": "Iste ipsa necessitatibus et perspiciatis blanditiis ducimus. Iusto quo consectetur non quo sint facere dolores architecto fugit. Veritatis asperiores nulla. Vel tempore quasi sapiente voluptatibus. Ea architecto eius laudantium error ullam consectetur. Illo et voluptates exercitationem molestiae nihil voluptate placeat. Eius qui delectus. Est velit fugit inventore ab molestias animi.",
      "titleList": "things to see and do in spain",
      "list": [
        "Molestiae hic explicabo.",
        "Ut rerum odit.",
        "Repudiandae nobis facilis.",
        "Asperiores consequatur qui cum.",
        "Commodi enim voluptatibus occaecati.",
        "Consequatur laudantium explicabo culpa."
      ],
      "img1": "https://backpacktraveler.qodeinteractive.com/wp-content/uploads/2018/09/paris-img-2.jpg",
      "img2": "https://backpacktraveler.qodeinteractive.com/wp-content/uploads/2018/08/h2-destination-2-img-2.jpg"
    },
    {
      "idDestination": 2,
      "id": "8526d121-2f92-4b2b-a35f-93d9ce9bd12f",
      "national": "australia",
      "title": "welcome to australia travel guide",
      "description": "Sunt eius quos aliquid porro. Quaerat repellat quo exercitationem officiis magni. Debitis dolor aliquam in ullam aperiam deleniti magnam repellat. Voluptatum doloribus laudantium ea sint ut. Sint autem similique vel. Excepturi placeat mollitia in voluptas. Pariatur et incidunt. Ut dolore alias explicabo nulla qui sunt velit. Natus ad dignissimos occaecati magni aut numquam veritatis. Quos dolorum qui repudiandae qui earum nulla rerum suscipit. Modi reprehenderit voluptatum quidem reiciendis dolor exercitationem ipsa officiis.",
      "titleList": "things to see and do in australia",
      "list": [
        "Voluptatem quia odit.",
        "Exercitationem aliquid sequi.",
        "Non pariatur ut.",
        "Et odio repudiandae tenetur.",
        "Vel consectetur similique et.",
        "Et provident quos debitis."
      ],
      "img1": "https://backpacktraveler.qodeinteractive.com/wp-content/uploads/2018/08/destination-autralia-single1.jpg",
      "img2": "https://backpacktraveler.qodeinteractive.com/wp-content/uploads/2018/08/destination-autralia-single3.jpg"
    },
    {
      "idDestination": 3,
      "id": "6d0dfeb1-d912-4298-9509-ed2a51109edd",
      "national": "peru",
      "title": "welcome to peru travel guide",
      "description": "Dolor rerum soluta asperiores eos est quibusdam illo quos. Ut perferendis excepturi quae magni nihil. Enim sunt explicabo. Unde dicta voluptatum a. Natus consequatur ad facere corrupti ut corporis. Autem magni quae quaerat aliquid voluptatem. Sed voluptatem consequatur iusto ab minus et est dolorem. Molestias delectus quas voluptates aut excepturi voluptas.",
      "titleList": "things to see and do in peru",
      "list": [
        "Voluptates voluptas voluptatem.",
        "Atque sit in.",
        "Dolor harum vero.",
        "Id voluptas voluptatem saepe.",
        "Velit sed et facere.",
        "Vel sequi suscipit voluptatem."
      ],
      "img1": "https://backpacktraveler.qodeinteractive.com/wp-content/uploads/2018/08/destination-peru-single2.jpg",
      "img2": "https://backpacktraveler.qodeinteractive.com/wp-content/uploads/2018/08/destination-peru-single3.jpg"
    },
    {
      "idDestination": 4,
      "id": "d5121e26-031a-4905-b3db-c7398b8e0e53",
      "national": "brazil",
      "title": "welcome to brazil travel guide",
      "description": "Sed nisi dicta aspernatur error corporis animi qui quo saepe. Eos et amet omnis dolores delectus quaerat culpa ut. Quod nostrum voluptatibus repellendus enim molestiae. Nihil quod sequi aut et vel. Ipsa qui omnis qui. Excepturi nihil excepturi impedit exercitationem molestiae fuga. Minima eveniet molestiae aut voluptas ut. Animi sit aut magnam pariatur tenetur. Quia provident ipsam voluptatem quas. Qui doloremque iste quaerat. Quidem quae vel soluta ut.",
      "titleList": "things to see and do in brazil",
      "list": [
        "Nesciunt autem quam.",
        "Veritatis qui odit.",
        "Dolorum necessitatibus et.",
        "Non quis molestiae neque.",
        "Voluptates vel voluptatem omnis.",
        "Dolores aut dignissimos porro."
      ],
      "img1": "https://backpacktraveler.qodeinteractive.com/wp-content/uploads/2018/08/destination-brazil-img1.jpg",
      "img2": "https://backpacktraveler.qodeinteractive.com/wp-content/uploads/2018/08/destination-brazil-img2.jpg"
    },
    {
      "idDestination": 5,
      "id": "23f0d67a-e8fe-487f-9781-a905029f64b0",
      "national": "united kingdom",
      "title": "welcome to united kingdom travel guide",
      "description": "Autem corrupti fugit consequuntur laboriosam aut et. Rerum molestias qui. Suscipit et nesciunt et temporibus earum dolore velit qui. Deleniti aspernatur voluptatem ut qui. Qui nostrum nulla amet ipsum debitis velit quaerat voluptas. Voluptas dolor totam. Officia laudantium quia enim consequatur et id. Possimus qui ratione. Rem est sed ut amet quod sed. Reiciendis et vel. Exercitationem voluptas et non occaecati.",
      "titleList": "things to see and do in united kingdom",
      "list": [
        "Libero et explicabo.",
        "Perferendis nostrum ut.",
        "Pariatur non aliquid.",
        "Sint ipsam in animi.",
        "Minima sed animi a.",
        "Repellendus rerum fugit doloribus."
      ],
      "img1": "https://backpacktraveler.qodeinteractive.com/wp-content/uploads/2018/08/h2-destination-1-img-1.jpg",
      "img2": "https://backpacktraveler.qodeinteractive.com/wp-content/uploads/2018/08/h2-destination-1-img-2.jpg"
    },
    {
      "idDestination": 6,
      "id": "e115dcc4-3c36-4d93-870c-9a69f2822468",
      "national": "italy",
      "title": "welcome to italy travel guide",
      "description": "Qui quo qui ea ipsam sequi officiis architecto veniam. Sed soluta aut est velit et deserunt quisquam maxime. Ut ipsam omnis nemo possimus facilis facilis voluptas ipsum. Consequatur eos debitis quaerat nihil sequi. Quod laborum dolores aut dolor qui autem. Voluptas quam ea dolorem est dicta nam. Ipsa adipisci sit quis facilis fugiat dolorum est. Excepturi ea est. Error odit veniam accusamus. Animi inventore minus qui quibusdam voluptas voluptatem amet incidunt omnis. Eos vel suscipit.",
      "titleList": "things to see and do in italy",
      "list": [
        "Mollitia praesentium eos.",
        "Nihil sint sed.",
        "Quia quas laudantium.",
        "Aliquid sed repellendus voluptatem.",
        "Ullam adipisci et at.",
        "Et nihil eum inventore."
      ],
      "img1": "https://backpacktraveler.qodeinteractive.com/wp-content/uploads/2018/08/destination-italiy-single3.jpg",
      "img2": "https://backpacktraveler.qodeinteractive.com/wp-content/uploads/2018/08/destination-italiy-single2.jpg"
    },
    {
      "idDestination": 7,
      "id": "e858b739-d2f6-4bb8-a165-847c3d4f128d",
      "national": "india",
      "title": "welcome to india travel guide",
      "description": "Possimus qui qui error aut. Consectetur eum repellat vero consequuntur est sint quis ipsa. Sit explicabo aspernatur vero voluptas. Sit delectus assumenda excepturi maxime deserunt. Sed repellat reiciendis ut eos voluptatem ratione voluptates sunt est. Dolores ipsam suscipit minima dolore animi. Nulla magnam nesciunt. Provident a in dicta laudantium recusandae culpa. Et veritatis quo consequuntur temporibus.",
      "titleList": "things to see and do in india",
      "list": [
        "Sed iste tempora.",
        "Quasi omnis quisquam.",
        "Iusto expedita quia.",
        "Repellendus maiores pariatur repudiandae.",
        "Porro asperiores ut enim.",
        "Commodi vitae facere voluptatum."
      ],
      "img1": "https://backpacktraveler.qodeinteractive.com/wp-content/uploads/2018/09/india-destination-img-3.jpg",
      "img2": "https://backpacktraveler.qodeinteractive.com/wp-content/uploads/2018/09/india-destination-img-4.jpg"
    },
    {
      "idDestination": 8,
      "id": "cd71d50e-7ab5-49dc-891c-6b0dd457553f",
      "national": "greece",
      "title": "welcome to greece travel guide",
      "description": "Omnis labore dolores. Voluptas ut voluptatem perferendis voluptatem accusamus. Commodi dolores exercitationem architecto quos qui quisquam soluta omnis reprehenderit. Nam cumque non iusto deserunt error accusamus. Magni aut sed et qui voluptates optio quibusdam quia. Doloremque voluptas earum nostrum ipsam voluptatem praesentium et ea. Non est et iure earum possimus consequatur eos et laudantium. Quidem expedita nesciunt cumque et suscipit aliquam dignissimos omnis mollitia. Sed molestiae dignissimos ratione temporibus animi et. Animi voluptates alias sed aut accusantium dolorem asperiores optio reprehenderit. Ea omnis ea eum est reprehenderit.",
      "titleList": "things to see and do in greece",
      "list": [
        "Magnam eaque culpa.",
        "Excepturi ut libero.",
        "Consectetur nobis molestiae.",
        "Perferendis corporis rerum maiores.",
        "Repellendus repellat expedita aut.",
        "Sed ipsa id aut."
      ],
      "img1": "https://backpacktraveler.qodeinteractive.com/wp-content/uploads/2018/09/Greek-img4.jpg",
      "img2": "https://backpacktraveler.qodeinteractive.com/wp-content/uploads/2018/09/Greek-img2.jpg"
    },
    {
      "idDestination": 9,
      "id": "a95fe24f-a321-447a-ab78-c5e3778dd5b1",
      "national": "france",
      "title": "welcome to france travel guide",
      "description": "Vitae est nihil dicta sed nihil pariatur cum est. Cupiditate consequatur corporis sint non numquam quia earum. Sint qui maiores sed sed. Unde ratione sint corporis ut dolorum est. Sint molestias ad consequatur velit natus et enim aspernatur saepe. Quibusdam dolorum voluptatem et dolor quam delectus ea sed. Voluptatum placeat mollitia et qui molestiae. Ipsam mollitia laborum nihil. Dolore placeat sapiente. Quo sequi voluptas ab non.",
      "titleList": "things to see and do in france",
      "list": [
        "Sapiente dolorum in.",
        "Temporibus id quia.",
        "Ex vero rerum.",
        "Quisquam maiores sapiente omnis.",
        "Consectetur ut vitae ut.",
        "Aut qui ut qui."
      ],
      "img1": "https://backpacktraveler.qodeinteractive.com/wp-content/uploads/2018/09/paris-img-2.jpg",
      "img2": "https://backpacktraveler.qodeinteractive.com/wp-content/uploads/2018/09/paris-img-2.jpg"
    }
  ],

  "typical-costs": [
    {
      "idDestination": 1,
      "id": "13c2e7c0-ef27-4cda-810d-373b7414ddbc",
      "accommodation": "Aut ipsam quidem. Qui eveniet blanditiis consequatur et rerum numquam quidem quia. In qui nihil aut at.\n \rIn sapiente animi qui in id animi. Aut repellendus quibusdam et eaque placeat velit aperiam veritatis consequuntur. Illum autem ex error labore repudiandae hic ad autem perspiciatis.\n \rAd veniam expedita minima pariatur recusandae non nobis numquam tempore. Vel voluptas illum officiis. Reprehenderit eum ab officia.\n \rAccusantium doloribus quos non enim placeat inventore et voluptatem. Optio qui voluptatem et quia cumque temporibus voluptatem ut. Eius nihil iure. Aliquam sit quidem ut adipisci impedit odit.",
      "food": "Quo quod ea dolor amet voluptatem. Iste sequi perferendis et et aut consequuntur. Quibusdam dolorum sit harum quos quis et ratione. Et hic sequi voluptas ex adipisci incidunt. Corporis aut est voluptate ut.\n \rVoluptatum voluptates enim eveniet sunt adipisci. Est voluptate nihil assumenda fugiat. Praesentium eveniet quasi qui qui ut ut quis officiis amet. Aliquid reprehenderit quos. Officia nam animi fugit et error fugit voluptatum tempora.\n \rMollitia iure eum ex et fugiat laborum numquam. Debitis ut nihil quibusdam architecto hic assumenda consequatur est illum. Dolor molestiae omnis.\n \rVoluptatum veniam hic fugit quae doloremque eum ratione officiis impedit. Tenetur cum debitis delectus soluta porro. Sunt ab voluptatem qui porro explicabo aspernatur iure. Voluptas ut mollitia voluptatem ut sed consequuntur aut quasi iusto.",
      "transportation": "Vitae ut vero ab quisquam sed. Ut nostrum qui deleniti ducimus consequatur. Architecto qui temporibus perspiciatis autem repudiandae nihil nobis et.\n \rSed fugit eum et necessitatibus omnis sed. Ullam vero excepturi nihil. A ipsa fugit possimus est consequatur.\n \rQuia ut ea. Voluptas repellendus eum iusto. Sequi laudantium atque numquam fugiat.\n \rId consectetur saepe. Vel unde sunt dolorem cum perferendis consequatur quam. Quia veritatis culpa non. Qui aut tempore et itaque ipsum nostrum tempora. Dignissimos accusamus officiis sequi quasi dolores odio et consequatur. Dolorem ipsam quia quasi rem.",
      "suggestedDailyBudget": "50-60 EUR / 52-62 USD (Note: This is a suggested budget assuming you’re staying in a hostel, eating out a little, cooking most of your meals, and using local transportation. Using the budget tips below, you can always lower this number. However, if you stay in fancier accommodation or eat out more often, expect this to be higher!)",
      "typicalCostImg": "https://backpacktraveler.qodeinteractive.com/wp-content/uploads/2018/08/h2-destination-2-img-5.jpg"
    },
    {
      "idDestination": 2,
      "id": "ce621c95-9df5-4842-9052-e1248d168131",
      "accommodation": "Eveniet ipsa sed ipsum tempore. Voluptatum deleniti eos dolor aut. Id sint qui est quod eos et corporis harum omnis.\n \rDolores eveniet vel veritatis numquam repellendus. Est blanditiis et quia minus quia quisquam iusto dolorem cupiditate. Et et beatae. Dicta voluptas commodi molestiae.\n \rMagni dicta sapiente quod itaque voluptatibus. Dolores adipisci eos accusamus. Sint libero impedit.\n \rEt omnis officia sunt consequatur qui ullam. Omnis accusamus molestiae. Suscipit excepturi voluptatum deleniti. Possimus aut ut. Dignissimos voluptates officiis dicta. Impedit ut rerum magni.",
      "food": "Ad reprehenderit saepe velit ratione. Vitae enim aut debitis. Est sed magni tempora voluptas non laboriosam dolore.\n \rSed aut autem officiis. Velit rerum harum similique voluptas fugit rerum perspiciatis eum. Dignissimos animi sit eius. Natus ducimus est doloremque animi recusandae vero exercitationem nobis.\n \rRatione accusantium perferendis sed est aut et in. Voluptatem quasi delectus. Animi ea sint. Expedita nesciunt minus est similique error aut repellendus et non.\n \rLibero officiis et in. Molestias eum laudantium. Optio sunt sint expedita vitae voluptatibus molestiae. Quisquam vel et ut at et aspernatur ratione fugit. Cum nostrum porro ab vel quas consequatur cupiditate.",
      "transportation": "Quo quisquam ab possimus perferendis facilis consequatur ut enim. Et officiis minus ducimus ratione. Similique corporis aliquid earum quia velit praesentium perspiciatis velit debitis. Ut voluptatum commodi culpa ut exercitationem.\n \rDignissimos similique vel vitae natus. Voluptatum soluta optio facere. Maiores illum consequatur beatae quidem quae. Vel aut tenetur velit. Voluptatem beatae rerum perspiciatis autem quos sunt. Illum iste eligendi laudantium ut nemo aspernatur quo nam.\n \rOmnis optio impedit. Voluptas est eveniet similique sed deserunt consectetur et debitis. Ut dolores dolores odio magnam amet consequatur quo amet eaque. Harum sapiente temporibus odio.\n \rEt tempore reiciendis harum esse et similique et veritatis eos. Cum rerum distinctio sint. Minus dolore qui. Fuga sint sed delectus commodi dolor reprehenderit quibusdam.",
      "suggestedDailyBudget": "50-60 EUR / 52-62 USD (Note: This is a suggested budget assuming you’re staying in a hostel, eating out a little, cooking most of your meals, and using local transportation. Using the budget tips below, you can always lower this number. However, if you stay in fancier accommodation or eat out more often, expect this to be higher!)",
      "typicalCostImg": "https://backpacktraveler.qodeinteractive.com/wp-content/uploads/2018/08/destination-australia-img-4.png"
    },
    {
      "idDestination": 3,
      "id": "3d05b87b-4eff-40c8-ab62-2dfaa675fa22",
      "accommodation": "A alias in itaque. Possimus dolorem repudiandae. Veritatis eum tenetur odio voluptate expedita iusto praesentium sed veritatis. Deleniti ea tenetur. Autem nesciunt velit rem velit et odit enim.\n \rItaque voluptatem saepe quos. Eaque sit corrupti voluptatem porro vitae aspernatur. Ut blanditiis commodi officiis aliquam dicta ut dolore impedit consectetur. Illo ut alias maiores soluta incidunt expedita magni. Omnis id officiis fugiat et. Pariatur quia quo tempora possimus dignissimos optio cum voluptas harum.\n \rVoluptatem illo aut iure. Ipsam sit vel. Aut dolores ipsa assumenda nobis dolorem voluptas.\n \rIpsa laborum provident voluptatem voluptatem sunt et. Totam voluptas quaerat. Id aspernatur magnam. Dolorum repudiandae ad nobis aut. Delectus consequatur et adipisci minima earum. Totam quisquam est dolor id.",
      "food": "Laudantium sapiente rerum necessitatibus quia tempore pariatur facilis. Harum similique est. Laudantium unde est magni.\n \rExcepturi a rerum velit quis in accusantium expedita et. In nulla dolorum voluptate. Sint ut ut consequatur minus architecto. Sapiente soluta temporibus nostrum ea error occaecati distinctio molestiae. Iure amet hic quis possimus et placeat dignissimos. Sit et et eligendi qui sit vel fugit.\n \rConsequatur facere doloribus voluptatem omnis accusantium. Blanditiis quia aliquid sed. Quod nihil voluptas sit quo. Hic dicta laboriosam accusamus. Temporibus et similique non ipsam est est cupiditate. Dolorum id et vero laboriosam excepturi sit tempora modi.\n \rQuam qui quam est facilis. Quod fuga recusandae magni nesciunt sapiente iusto fugit non. Magnam reprehenderit cupiditate ducimus eaque illum.",
      "transportation": "Magnam quis sapiente sint est minima. Illo aliquam rem labore atque blanditiis. A ullam aut alias voluptatum neque iusto voluptatem est consequatur. Placeat consectetur sequi libero rerum omnis sapiente non. Eius est nisi rerum autem repellat. Itaque saepe odio.\n \rConsequuntur quibusdam voluptas similique. Et est est vel officiis commodi non. Voluptas culpa esse asperiores quis quas quis. Aut omnis quae.\n \rProvident aperiam ratione. Voluptatibus voluptas aut deleniti. Facilis a sed quisquam veniam facilis nesciunt ad.\n \rQui quod rem facere nisi vitae architecto minus. Occaecati vel qui harum perspiciatis ea reiciendis enim illo molestiae. Porro recusandae neque omnis quam ab cumque. Reiciendis beatae temporibus enim iure placeat repellat similique consequatur.",
      "suggestedDailyBudget": "50-60 EUR / 52-62 USD (Note: This is a suggested budget assuming you’re staying in a hostel, eating out a little, cooking most of your meals, and using local transportation. Using the budget tips below, you can always lower this number. However, if you stay in fancier accommodation or eat out more often, expect this to be higher!)",
      "typicalCostImg": "https://backpacktraveler.qodeinteractive.com/wp-content/uploads/2018/08/destination-peru-img-4.png"
    },
    {
      "idDestination": 4,
      "id": "6ed01e8a-bcef-410a-a4ff-7f8ce1c64215",
      "accommodation": "Numquam error et et quia molestias non officia sed sit. Voluptatem voluptas quis qui possimus modi est odio saepe quam. Aut et pariatur deserunt neque quia odit animi hic. Voluptatem saepe aut et et sed maiores.\n \rSapiente blanditiis soluta minus et enim totam quae qui ut. Enim minima distinctio quam omnis distinctio et fugiat molestiae. Quis ut suscipit dolorum nobis error. Molestias qui sed esse optio.\n \rQuisquam quia tempora enim. Recusandae delectus quod maiores reiciendis atque placeat aperiam quia. Inventore iure rem et. Cumque magnam ut qui.\n \rNostrum voluptate praesentium laboriosam unde. Officia dolores aut sed sapiente ipsa minus tempore. Sunt inventore ab libero quo delectus accusamus.",
      "food": "Neque ut officia distinctio adipisci libero. Excepturi rerum cupiditate assumenda rerum eos rem veniam a possimus. Fugiat vel voluptatem ea.\n \rAccusamus rerum corrupti error quis voluptates ut perferendis. Tempore natus voluptatem et provident sint nulla necessitatibus cumque eligendi. Magni et omnis totam similique. Vero qui impedit consequatur quas qui voluptatem sed maxime non. Soluta nesciunt ea voluptatem fugiat velit velit laudantium beatae blanditiis. Excepturi nihil laudantium ea.\n \rQui aliquam libero vel in nam reprehenderit consectetur doloribus et. Porro eaque soluta quis ut rem id doloremque amet voluptatem. Eum adipisci non ad et et enim. Dolor enim non sunt velit magnam quia quo quisquam quia.\n \rDolores velit repellendus vel rerum. Accusantium consequatur sed autem autem nostrum reiciendis alias qui officia. Cupiditate nam quo soluta aliquam sint asperiores voluptas. Cum iure optio.",
      "transportation": "Voluptatem non ipsum molestiae aliquam et pariatur. Soluta laudantium cumque. Rerum dicta officiis voluptatem ipsam. Consequatur ea voluptatibus quasi alias iste porro. Non ut ea fugit molestiae totam corporis. Accusantium quam excepturi eos exercitationem.\n \rMollitia et eum occaecati dolor. Eos consequatur repellendus quia dolor quia quaerat provident sint. Ab alias voluptatum dolores dolorem aut necessitatibus qui.\n \rDolores deserunt earum molestiae vel quibusdam cum quia. Quisquam ratione cum est omnis libero qui quidem perspiciatis unde. Numquam ratione vel dolore iure temporibus voluptatem. Cumque non quo voluptatem. Facere dolorum voluptatem enim corrupti ducimus et quod aperiam iusto.\n \rEst rerum quo eum architecto ad perspiciatis molestiae culpa. Molestiae quibusdam sed ea iusto. Eaque aliquam eos eos qui ut et asperiores. Ut quia dolor minus dolores explicabo quod voluptatem quisquam. Et earum omnis modi animi earum velit.",
      "suggestedDailyBudget": "50-60 EUR / 52-62 USD (Note: This is a suggested budget assuming you’re staying in a hostel, eating out a little, cooking most of your meals, and using local transportation. Using the budget tips below, you can always lower this number. However, if you stay in fancier accommodation or eat out more often, expect this to be higher!)",
      "typicalCostImg": "https://backpacktraveler.qodeinteractive.com/wp-content/uploads/2018/08/destination-brazil-img-4.png"
    },
    {
      "idDestination": 5,
      "id": "f0b38aab-bd38-4fba-a205-e578609fc0b5",
      "accommodation": "Non vel non sit. Labore eos ut consequatur quaerat sapiente alias qui ipsa et. Quis dolores eaque qui. Autem enim dolorem nisi dolorum nesciunt quia modi.\n \rVero velit dignissimos occaecati commodi ut minus fugiat. Consequatur perferendis rem sint rerum. Eum libero exercitationem nobis eius dolores soluta aut natus esse. Quam soluta dolorem. Est et voluptas placeat ullam quasi.\n \rOccaecati sapiente expedita. Deserunt consequatur quaerat nesciunt rerum. Consequatur quas qui natus expedita omnis ea minima et consequatur. Nostrum perferendis sint. Quod fuga sint commodi laudantium non.\n \rIncidunt dolore dolorem voluptates quasi possimus cupiditate sint. Velit commodi minima a adipisci dolorem. Dolorem est provident error dolor quis necessitatibus excepturi est quos. Possimus qui voluptatem. Debitis delectus est. Molestiae perspiciatis qui temporibus.",
      "food": "Dolorem eius dolores a modi. Soluta voluptas voluptatum ut aspernatur alias dolorum optio sit. In magnam voluptatem dignissimos quo sed neque. Labore id temporibus et. Aut est sunt ullam velit placeat.\n \rQuos quae aut sed quo quo ea numquam. Dolorem suscipit libero et ut cum. Saepe ut nesciunt maxime veritatis mollitia magni nam voluptatem temporibus.\n \rNulla fugiat voluptas explicabo id eaque dolore voluptas. Aut blanditiis nostrum iusto consequuntur blanditiis. Facilis ea tempora et ut aut dolor quisquam eius. Quia delectus quam quo. Inventore et consectetur quas ea quis. Qui et voluptatem ratione quis aut reprehenderit rerum ut tenetur.\n \rRerum praesentium quisquam veritatis et vel consequuntur non. Sint nostrum quia. Provident maiores ut dolorem aut ducimus sit. Minima et temporibus.",
      "transportation": "Iure quia modi deleniti consequatur odio adipisci asperiores maxime. Veniam qui dolor sit voluptas eligendi id. Rerum quis unde perferendis perspiciatis voluptate sapiente natus. Quia quibusdam voluptatem. Quia nihil voluptatem delectus necessitatibus fugiat. Voluptatibus ab perspiciatis in sint modi facilis accusantium veritatis.\n \rUt eveniet voluptas perferendis nesciunt recusandae. Quia excepturi tempore hic sapiente molestiae et officiis ipsa. Quisquam qui sed modi maxime in quibusdam hic et quos.\n \rSunt eos labore sit aut eum non. Rerum totam autem dolore enim voluptate minima. Quod rerum ipsam et sequi eaque eveniet aut porro. Qui nobis dicta nemo dolore distinctio qui. Eveniet aut repellat ipsam perferendis quia molestias veritatis optio exercitationem. Saepe totam voluptatibus.\n \rPorro et eum cum. Quia sequi asperiores sit. Voluptas cum amet distinctio earum id. Numquam aliquid omnis facere nostrum hic necessitatibus et consequuntur praesentium. Rerum maiores minus corrupti fugiat non minima. Qui quia est quia culpa earum.",
      "suggestedDailyBudget": "50-60 EUR / 52-62 USD (Note: This is a suggested budget assuming you’re staying in a hostel, eating out a little, cooking most of your meals, and using local transportation. Using the budget tips below, you can always lower this number. However, if you stay in fancier accommodation or eat out more often, expect this to be higher!)",
      "typicalCostImg": "https://backpacktraveler.qodeinteractive.com/wp-content/uploads/2018/08/h2-destination-1-img-3.jpg"
    },
    {
      "idDestination": 6,
      "id": "7074c49c-edc9-4bbe-b568-94f96a5163d9",
      "accommodation": "Quibusdam dolor mollitia quod a eos consectetur. Hic veritatis molestias quam sed dolores sapiente aperiam perferendis aut. Voluptatem sint et perferendis. Error totam maxime ut assumenda ducimus placeat non deleniti vel. Et quas dolorem. Ut nemo delectus.\n \rLabore aut officiis doloremque. Voluptas ut ut pariatur sed sunt quia. Atque error amet unde omnis nisi numquam. Labore id nam optio in. Voluptatem voluptas perspiciatis culpa voluptatem voluptatem laboriosam facilis. Deleniti enim magnam repudiandae porro culpa quisquam quae.\n \rCorrupti ut corrupti sed. Officia deleniti porro eveniet omnis laudantium facilis soluta. Suscipit provident illum alias explicabo. Suscipit nobis neque doloremque illum. Rerum at assumenda modi doloribus aspernatur dolores ea numquam. Ducimus quia et est.\n \rTotam est qui. Adipisci quis repellendus. Consequatur iste quo doloremque architecto laudantium ut iusto ex officiis. Quidem dolores omnis ab.",
      "food": "Voluptatem facere libero. In et fugit ipsum recusandae molestias doloremque. Unde rerum iusto qui qui alias tenetur ut inventore ea. Rerum aut quisquam quia quisquam. Et cupiditate excepturi minus.\n \rPorro placeat vero. Similique aut qui sed quia repellendus vel. Optio velit eveniet distinctio cumque. Nulla repudiandae voluptas ipsum quis doloribus ullam nesciunt perspiciatis.\n \rQuidem excepturi beatae praesentium vel officiis. Et dolore quasi excepturi at necessitatibus tempore unde nobis veritatis. Ipsa id occaecati quis. Quibusdam aspernatur rerum deleniti perferendis nihil temporibus ea qui. Cumque optio ipsum.\n \rOfficiis ea ut quibusdam vel. Recusandae ut maiores ratione nihil labore et asperiores assumenda. Labore id molestiae vitae repellendus totam distinctio voluptas. Ab cumque autem aut qui aperiam atque accusamus unde ut.",
      "transportation": "Rerum perferendis excepturi culpa. Enim omnis ab est. Nam optio cupiditate nihil at. Est tenetur natus id. Consequatur temporibus quo dignissimos voluptas ad maxime qui ut.\n \rEst consequatur necessitatibus et et. Voluptatem odit adipisci. Deserunt odit ipsum accusantium commodi ullam voluptatum ipsa. Mollitia modi in nulla eos. Voluptatem qui et sequi laboriosam expedita eum placeat. Voluptatem est harum quos.\n \rEst molestias consectetur minus quidem ut rem molestiae. Et est cum nostrum earum. Sed repellendus voluptas praesentium occaecati iure.\n \rAb error molestiae. Repudiandae placeat quo quia doloremque et eligendi est. Exercitationem molestiae cupiditate non ut repellat non ut rerum. Mollitia sint corporis officiis voluptates exercitationem sed. Ut velit ipsam eos qui corrupti eum sed perspiciatis.",
      "suggestedDailyBudget": "50-60 EUR / 52-62 USD (Note: This is a suggested budget assuming you’re staying in a hostel, eating out a little, cooking most of your meals, and using local transportation. Using the budget tips below, you can always lower this number. However, if you stay in fancier accommodation or eat out more often, expect this to be higher!)",
      "typicalCostImg": "https://backpacktraveler.qodeinteractive.com/wp-content/uploads/2018/08/destination-italy-img-4.png"
    },
    {
      "idDestination": 7,
      "id": "e6689e52-cdff-465a-83d1-ac06085db25b",
      "accommodation": "Facilis magnam voluptates. Sit temporibus corporis aut fugit. Eveniet eligendi harum quasi unde.\n \rVoluptates aspernatur quo facilis. Impedit at a aut et unde. Et sunt voluptatem ea. Omnis sit commodi. Temporibus consequatur voluptas provident optio explicabo aliquam sint eligendi.\n \rRatione ab nisi aperiam. Repellat aut doloremque. Non ut sequi. Magnam tempore perspiciatis dolore pariatur qui laborum occaecati quod quis. Cum occaecati voluptates optio omnis excepturi et error est consequatur.\n \rDoloremque dolore nostrum minima quo odio odio. Sed quasi nostrum eos nihil nobis ratione ut deserunt. Ex minima sit totam eaque. Molestias reiciendis dolores distinctio aperiam est. Illum consequatur quis molestiae molestias qui ab suscipit.",
      "food": "Omnis omnis nemo voluptate molestiae ea enim sunt explicabo. Facere qui deserunt esse blanditiis consectetur repellendus ullam voluptatibus. Labore impedit nam beatae voluptatem dolorem voluptatum ullam sunt voluptatem. Dolores sequi est quod praesentium ex adipisci asperiores repellat illum.\n \rEius et quibusdam debitis dolor ut officiis fugit expedita. Repellendus sequi quod deleniti repellat ea quo velit. Ex sed nesciunt adipisci voluptates et aut. Mollitia aut praesentium sunt natus numquam qui sed rerum assumenda. In quos similique quo in molestiae sint placeat.\n \rEt tenetur aliquid vero ut et et consequatur exercitationem. Nostrum in labore eligendi qui perferendis. Dolor et voluptate laudantium.\n \rVel iure est velit eos. Aperiam reprehenderit ullam. Soluta aspernatur atque laborum beatae non perspiciatis aut natus. In soluta sunt id iusto sunt et recusandae quaerat fuga. Et quia quibusdam qui dignissimos expedita perspiciatis qui ratione placeat. Ipsa molestiae rerum est impedit temporibus odio necessitatibus eveniet debitis.",
      "transportation": "Dignissimos consequatur officiis ut voluptatem deserunt et quisquam. Velit repellat sed accusantium. Distinctio ut vero atque vel vero quod excepturi iste alias. Minima perspiciatis sint.\n \rNon commodi ut id sint inventore est. Nulla voluptatibus animi officia animi iure incidunt esse tempore nulla. Aperiam non labore quam et ipsum. Occaecati voluptatum velit eum nostrum qui veniam voluptas libero in.\n \rVel placeat quia alias sed voluptate sapiente. Qui sint id rem tempora autem tempora. Aut voluptates repellat natus in nesciunt quibusdam maxime. Impedit in sapiente reprehenderit ut quo dolore debitis dolore. Fugit ipsa dolores aut reprehenderit.\n \rNam corporis labore unde. Autem pariatur quo atque quisquam. Natus sed impedit magnam placeat et quo enim.",
      "suggestedDailyBudget": "50-60 EUR / 52-62 USD (Note: This is a suggested budget assuming you’re staying in a hostel, eating out a little, cooking most of your meals, and using local transportation. Using the budget tips below, you can always lower this number. However, if you stay in fancier accommodation or eat out more often, expect this to be higher!)",
      "typicalCostImg": "https://backpacktraveler.qodeinteractive.com/wp-content/uploads/2018/09/destination-india-img-2.png"
    },
    {
      "idDestination": 8,
      "id": "66469417-d4d8-4fb0-a322-f69d3e11012d",
      "accommodation": "Adipisci corporis architecto sapiente quod odio omnis. Natus commodi vel. Velit voluptas qui. Animi occaecati sapiente fugit sunt ea.\n \rNumquam modi necessitatibus rerum officia facilis consectetur. Nihil incidunt tempore tempora nobis vel repudiandae et. Sunt doloremque eligendi provident neque numquam. Consequatur voluptatum voluptatum eaque earum temporibus modi. Est perspiciatis aut doloremque nulla voluptate facere. Accusamus sed et quia error sunt cupiditate corrupti.\n \rAperiam alias minus voluptates iste aut aut est quo. Sint quas nam qui deleniti nihil sint corporis omnis ut. Laudantium pariatur ut. Omnis maiores consequatur quis ducimus.\n \rAut iure eum repellendus. Sit cumque consequatur. Cupiditate quo illo nam aut sequi similique qui.",
      "food": "Aperiam velit eligendi neque sit aliquid sit minima. Et natus et autem aliquam voluptas est deleniti a mollitia. Aut enim reiciendis quaerat. Occaecati et iusto modi dolorem aliquam et quaerat.\n \rMollitia saepe facilis. Dolore impedit ipsa ducimus officia ipsum culpa ut et. Harum quibusdam est. Reprehenderit reprehenderit tempora sint neque est reiciendis nostrum enim. Adipisci harum ea.\n \rAut unde ut cupiditate magnam dolorem quae fugit. At consequatur qui. Voluptatum sequi eligendi et officiis harum error libero.\n \rQuasi ab itaque quis inventore ipsam voluptas. Qui repudiandae voluptatem laborum sint et sed eius voluptas. Quasi ut odit assumenda doloribus dolorum quisquam. Non repudiandae tempora nulla fugit.",
      "transportation": "Dicta voluptatem voluptatem perferendis numquam expedita aspernatur ad. Ipsam cum temporibus illum sunt officiis molestias. Qui et saepe atque sint maxime quibusdam ducimus blanditiis rem. Et totam et. Amet voluptas reprehenderit voluptas.\n \rRerum ipsum et sit qui consectetur qui culpa. Sunt ipsam blanditiis architecto voluptatem optio. Quo dolor dolorem ut culpa minus dolores est. Provident ea voluptate dolores quo. Asperiores voluptas omnis mollitia ut cumque est quasi omnis commodi.\n \rDolorem voluptatem aliquam quo aut nobis. Pariatur ratione ab quibusdam non natus omnis nisi. Amet cumque dicta.\n \rAut aliquid et aspernatur debitis corrupti est necessitatibus dicta praesentium. Alias expedita eaque. Tempore quos modi vero perferendis adipisci quia esse incidunt. Sunt et nulla. Voluptas voluptas vel expedita. Velit voluptatem et nihil.",
      "suggestedDailyBudget": "50-60 EUR / 52-62 USD (Note: This is a suggested budget assuming you’re staying in a hostel, eating out a little, cooking most of your meals, and using local transportation. Using the budget tips below, you can always lower this number. However, if you stay in fancier accommodation or eat out more often, expect this to be higher!)",
      "typicalCostImg": "https://backpacktraveler.qodeinteractive.com/wp-content/uploads/2018/09/grees-img-4.png"
    },
    {
      "idDestination": 9,
      "id": "468ed056-862e-44f0-862f-8cc96d77e3e9",
      "accommodation": "Aut nihil ipsum. Sit provident itaque voluptas cum rerum nihil omnis dolor deleniti. Et qui dicta voluptatem. Dolor consectetur at vero et sint quam error ipsa dolorem. Alias corrupti sit molestiae earum suscipit. Odit quia nam cupiditate aspernatur aperiam distinctio eius.\n \rIllo consequuntur iusto qui ipsum optio. Ea voluptas voluptatibus cum. Facilis consequatur qui nihil voluptas. Et et temporibus repudiandae nam numquam porro.\n \rId maiores et qui tempora. Magni nostrum quae repellat et aspernatur itaque aut amet. Libero voluptas ut quidem occaecati libero consequuntur cupiditate. Minima velit tenetur quaerat delectus nobis. Aut harum est ut iusto natus sequi voluptas.\n \rAutem corrupti culpa beatae ut enim qui quibusdam. Provident tenetur quam. Rerum consequatur ut libero ipsam culpa. Iure repudiandae porro ut. Voluptatem quam labore numquam id velit impedit quod.",
      "food": "Recusandae neque itaque animi earum nam laboriosam laborum. Ut ipsa rerum vel aut autem. Atque labore aliquid quos quae quod.\n \rUnde neque necessitatibus quia et est ducimus qui illo. Voluptate id placeat rerum commodi est inventore quisquam soluta. Deleniti consectetur quis perspiciatis molestiae sequi iusto. Architecto quia eum et quia qui minima sint officiis ipsam. Nihil assumenda quam architecto distinctio quo et et rerum error. Ex unde aliquid alias quos rerum consectetur quod earum.\n \rEum sint iste qui officiis. Assumenda vel vel maxime ut non possimus. Provident odit corporis eaque id itaque. Architecto aut quis temporibus dolorem. Quae illo odit.\n \rIn ut ea. Nam quidem soluta deleniti reprehenderit harum nostrum vel quis dolorum. Consequatur officia deserunt minus aut. Ipsam minus quam iste quia dolor et. Sit non harum sint dolorem architecto voluptatem delectus aut quis. Itaque tempore veniam ad perspiciatis.",
      "transportation": "Maxime quo culpa. Corrupti unde voluptatem ut et necessitatibus quia. Enim dolorem id et repudiandae deleniti sit dolor. Est omnis dolorem illum voluptas eos et facilis. Iste et ad inventore.\n \rAut magnam voluptate cum saepe et rem tempora. Commodi dolor est quibusdam quod velit sed iure corrupti minus. Minima fuga at.\n \rRerum laborum qui quasi dolorum. Qui dolore voluptates vitae cupiditate. Voluptas fugit sit optio ratione aut blanditiis voluptates deserunt aut. Quia quo ut officia quaerat omnis. Impedit blanditiis saepe ullam inventore eligendi corporis praesentium sint dolorum.\n \rQuia sed praesentium asperiores sint numquam. Repellendus velit atque mollitia et. Dolorem rerum perspiciatis nulla dolor dolore voluptatum aut.",
      "suggestedDailyBudget": "50-60 EUR / 52-62 USD (Note: This is a suggested budget assuming you’re staying in a hostel, eating out a little, cooking most of your meals, and using local transportation. Using the budget tips below, you can always lower this number. However, if you stay in fancier accommodation or eat out more often, expect this to be higher!)",
      "typicalCostImg": "https://backpacktraveler.qodeinteractive.com/wp-content/uploads/2018/09/paris-img-4.png"
    }
  ],

  "budget-tips": [
    {
      "idDestination": 1,
      "id": "11f21cd8-7c88-46cc-b211-5fdaddaedd0e",
      "getTheMenu": "Temporibus tenetur voluptatem sit soluta in omnis at. Natus velit perferendis tenetur officiis porro. Ad unde exercitationem nesciunt voluptas sequi. Vel aut deserunt sed provident eos est sapiente ad eum.",
      "rideWithUber": "Sit et ex excepturi maiores voluptates in id. Qui reiciendis nihil iusto ex provident ad neque. Quas qui nostrum aut fugit. Iusto hic maxime quae ea quos occaecati aut. Corporis laboriosam accusantium. Reiciendis sed rerum impedit est consequatur aperiam eos.",
      "getCityPasses": "Non enim qui reprehenderit animi. Quam rerum ea blanditiis est error necessitatibus ut non. Praesentium ut id quaerat quae nobis.",
      "couchsurf": "Et temporibus ut dolores accusantium dolorem. Qui cum reiciendis tempora quas aut. Aut quibusdam explicabo praesentium minus dolores. Cumque voluptates sed qui dolor ea molestiae."
    },
    {
      "idDestination": 2,
      "id": "8a8b85ac-d2b0-40a3-9b3b-dfd1722ba820",
      "getTheMenu": "Quo sapiente rem consequuntur et. Esse ipsum dolor. Voluptas explicabo eius optio modi temporibus. Laborum recusandae aliquid iusto perspiciatis qui aut natus in. Beatae consequuntur omnis est veniam assumenda praesentium.",
      "rideWithUber": "Quae ipsum minus et sint iure iusto quo recusandae. Consectetur dolorem officia temporibus itaque itaque nesciunt ea quae neque. Officiis porro rerum numquam voluptatibus quibusdam.",
      "getCityPasses": "Et harum provident ea maxime et placeat quibusdam consequatur modi. Voluptas autem deleniti enim rerum saepe aut numquam fugit esse. Quia voluptatem asperiores nesciunt dignissimos a velit et est. Molestiae quibusdam debitis est.",
      "couchsurf": "Similique fuga aut. Totam rerum qui vero ea quo unde sit quo. Voluptates culpa dolorem nulla pariatur sint. Similique nulla est iure quisquam distinctio porro. Nam consectetur at. Modi id beatae qui aut qui inventore dolores."
    },
    {
      "idDestination": 3,
      "id": "d24ccab6-2793-4d13-95ac-2fa80ad81573",
      "getTheMenu": "Ab reiciendis aliquid amet non et. Atque qui doloremque id et similique minus. Ex blanditiis est aut inventore ipsum veniam ipsum. Nostrum aliquam molestias. Cumque earum fugiat et cumque occaecati enim sit voluptatem.",
      "rideWithUber": "Ducimus in quo officia. Aut est voluptatum quisquam non. Illum itaque vero quibusdam. Ipsam quia sed odit impedit iusto et explicabo exercitationem ea.",
      "getCityPasses": "Error et aut sed. Cum incidunt enim dolores est iste ut aut nostrum. Qui voluptatem consequatur nemo nihil sit.",
      "couchsurf": "Ratione dolores consequatur totam in nisi a. Harum molestiae omnis quasi minima delectus. Consequuntur itaque nostrum sit qui non quos reiciendis corporis sit. Ea quam autem aut magnam enim porro."
    },
    {
      "idDestination": 4,
      "id": "b0d7633e-d63b-41a8-9520-01d955dee7b5",
      "getTheMenu": "Perspiciatis ullam quod dolores deleniti nesciunt quia minima nostrum harum. Sed totam voluptatem voluptate voluptate et. Ut quo saepe sapiente magni corporis. Sequi eum voluptatem perspiciatis assumenda qui quidem dolorem similique. Ipsum est laudantium consequuntur sed.",
      "rideWithUber": "Ut a quisquam voluptas voluptas. Nam dolorum qui. Aut dolorem pariatur molestiae aut ut eaque nobis. Dolorum quia enim consequatur quae ex est. Quia nihil et soluta nam sed placeat omnis quibusdam. Aut alias fugit quod.",
      "getCityPasses": "Voluptas voluptatem sunt. Eveniet velit quo quis. Vel eaque nesciunt aut adipisci provident enim voluptatem. Laudantium laudantium dicta optio voluptates. Fugit possimus impedit quaerat blanditiis ducimus. Necessitatibus error minus molestias.",
      "couchsurf": "Iste et enim. Numquam ex debitis ut. Voluptatem recusandae eos aut quis numquam exercitationem officiis. Ut quas harum quia non dolorem non delectus tenetur enim. Tempora ducimus qui ipsum omnis quaerat quia. Nesciunt itaque necessitatibus harum quia veniam ad quia."
    },
    {
      "idDestination": 5,
      "id": "97cc17b7-4b19-488f-bdb1-a400042ec1de",
      "getTheMenu": "Quidem qui velit laboriosam officiis et ipsum et et consectetur. Reprehenderit cumque a quia vel aut debitis eligendi ipsam ipsam. Animi vel est.",
      "rideWithUber": "Sint doloremque laboriosam sint quo reiciendis soluta expedita. Sit excepturi odit. Id est qui voluptatem et omnis. Rem quisquam id. Corporis nemo sed sint quod nihil autem nulla eaque iure. Possimus maxime quas ut odit unde.",
      "getCityPasses": "Laudantium aut consequatur rem voluptas quibusdam rerum consequuntur eligendi. Et minima et incidunt dolorem veritatis culpa nisi debitis. Ullam magni hic. Eligendi in sint dolorum.",
      "couchsurf": "Dolor est est sed explicabo perferendis in maxime. Quia consequatur aliquam ut dolorem nihil sed. Tempore vero molestiae veniam perspiciatis hic eius quasi cumque. Magni ut exercitationem et."
    },
    {
      "idDestination": 6,
      "id": "fa2d84f8-e833-47a4-9fa7-d3c5e8e178b8",
      "getTheMenu": "Temporibus eum dolore modi aut odio sit non est. Qui aut molestias omnis tempore. Sit praesentium eum quo et aspernatur ipsam quasi. Eos rerum quia rerum vitae sit a inventore necessitatibus a. Ex laudantium minima ut consequuntur modi.",
      "rideWithUber": "Ea praesentium nisi molestiae iure voluptatibus velit dolores. At veritatis quibusdam. Non libero amet cumque.",
      "getCityPasses": "Sit libero cum. Perspiciatis doloribus ipsam quaerat eos et reprehenderit earum distinctio expedita. Voluptatem quos eum a rem non est explicabo praesentium quaerat. Quod alias animi eaque sint occaecati et consectetur consequatur. Voluptatem ab harum aliquid temporibus doloribus quam accusantium.",
      "couchsurf": "Quam dolorem in modi. Expedita perspiciatis soluta eos praesentium. Error et voluptatem voluptates et fugit unde quae et facilis. Mollitia ab non dolorum laborum. Ipsam alias voluptatum animi cumque aut aliquam exercitationem. Necessitatibus possimus modi voluptas."
    },
    {
      "idDestination": 7,
      "id": "4ed590dc-2986-4fa2-88e1-497870e5f9c1",
      "getTheMenu": "Saepe ipsam in velit voluptas expedita quia quo et. Nemo sapiente quia adipisci qui quis laudantium fuga voluptatum. Itaque nihil architecto quod delectus soluta et facere sapiente ut. Fuga voluptatem unde ipsum autem perspiciatis aspernatur repellendus quam nostrum.",
      "rideWithUber": "Rerum in voluptatem suscipit in et quia. Sed aut veritatis. Eos necessitatibus exercitationem atque mollitia.",
      "getCityPasses": "Est accusantium atque deserunt voluptate officiis magnam et quidem fugit. Consectetur quos fugiat velit vitae repellendus minus. Mollitia modi magni modi qui. Voluptatem ullam molestiae molestiae reprehenderit quae aut provident quaerat. Iure rerum minus. Culpa doloremque numquam a ea ea ut illo.",
      "couchsurf": "Amet ut nemo. Tempore totam facilis et beatae non aut modi voluptas magni. Fugiat qui nemo fugit qui et ut sit. Illo id dolore odit quia quod sapiente assumenda officiis. Atque nesciunt voluptatem est. Sunt quidem illo ea minus ea."
    },
    {
      "idDestination": 8,
      "id": "8e0c2acf-e0f7-4e64-807d-0f11297f8309",
      "getTheMenu": "Eveniet neque omnis. Nesciunt debitis qui corporis fuga quis. A rerum dolores autem ut adipisci. Porro natus repellendus itaque nesciunt. Et modi iusto vero enim esse non dolor expedita.",
      "rideWithUber": "Quis quod dolorum et voluptas laborum numquam. Iusto sed sit modi et. Libero est architecto voluptas. Ut sint laudantium. Porro placeat doloremque nihil odit. Ut cupiditate enim ea ut et ut.",
      "getCityPasses": "Accusamus sit tenetur voluptatem dolores est. Et molestiae praesentium dolor. Nulla quae quos ut.",
      "couchsurf": "Veritatis in id. Sapiente sed et dolores. Quisquam minima qui rerum in nesciunt id earum. Rerum inventore vero molestiae."
    },
    {
      "idDestination": 9,
      "id": "5d7c0430-b5fb-44da-bed2-fda0221d377b",
      "getTheMenu": "Autem et dicta et. Nobis ea sit repellendus ullam. Quod et aut. Provident et doloribus ut sit recusandae unde. Consequatur non occaecati harum ad nam est iure. Et dolores harum.",
      "rideWithUber": "Quas exercitationem vitae aut eveniet temporibus soluta est. Quisquam quis non dolorem porro adipisci quae aut velit. Maiores quo dicta dolor ut saepe rerum vel similique natus. Sed blanditiis non.",
      "getCityPasses": "Beatae dolorem odit qui architecto voluptates maxime praesentium omnis eum. Vero expedita molestiae sunt dolorem. Error quo laudantium doloremque nam accusantium praesentium qui. Iure alias incidunt molestias vel distinctio at. Aliquid sint id assumenda facere voluptate quod error.",
      "couchsurf": "Consequatur et voluptas voluptates vel aut pariatur temporibus facilis illum. Enim voluptates eos. Assumenda laborum nesciunt."
    }
  ],

  "related-guides": [],

  "related-articles": [
    {
      "idDestination": 1,
      "id": "c38136b2-f8af-4be3-9348-55686f4a1e84",
      "title": "what can i expect from spain",
      "blogList": [],
      "description1": "Et explicabo ratione omnis est quo praesentium sint. Impedit minima aperiam voluptas rem aut ut quia id nisi. Voluptas nisi est accusantium et eos natus placeat natus vitae. Quo nostrum qui repudiandae officiis qui saepe in sit.\n \rQuo corporis non in iusto dolores quis vel eum. Sit aperiam molestias id porro doloremque est qui incidunt. Consequatur dignissimos asperiores magni voluptatem amet veritatis earum eos doloremque. Ex quo voluptatem qui et doloremque. Quisquam molestias hic qui qui omnis dolor temporibus assumenda eum. Ex hic illo non sed consequatur sed.\n \rNihil qui neque laboriosam repellendus aut. Qui perspiciatis velit. Repellat impedit aut.\n \rSaepe voluptatem consequatur labore magnam facere dignissimos quo. Dolores necessitatibus saepe magnam minima ratione et molestiae distinctio. Unde occaecati sed hic aperiam exercitationem. Eligendi commodi natus praesentium accusamus hic sed laudantium aut. Nulla et dolorum consequuntur ipsum asperiores quibusdam minima et omnis.",
      "description2": "Molestiae ea cum est ut ipsam atque sit. Non quod omnis sit consequatur officia amet. Harum est repellendus fugiat alias ratione. Sed error sed et voluptas qui officia. Praesentium et aut soluta reiciendis labore et. Sed error blanditiis cum voluptatem asperiores unde exercitationem.\n \rLaborum dicta consectetur est dicta laboriosam. Eaque deleniti pariatur atque aperiam numquam rerum non adipisci cupiditate. Consequuntur quia aperiam voluptas magni nihil cupiditate iure sed.\n \rQui aspernatur sed voluptas laborum libero. Nihil harum commodi delectus. Sint sit quia ipsa ullam perspiciatis laudantium voluptatem sint quia. Eius et accusamus placeat a eum debitis ut.\n \rAnimi perspiciatis perferendis sit nesciunt quam ad est autem. Consectetur quia tenetur ut dolor. Dolorem iste vel earum beatae. Iusto ut omnis. Ad ex ab architecto labore voluptatem. Rerum consequatur eum natus cumque eius cum veniam quia aut.",
      "categories": ["fishing", "overnight"],
      "hearts": 0,
      "comments": 0,
      "time": 1666554133234
    },
    {
      "idDestination": 2,
      "id": "fc6d7466-4acb-4830-8dd1-ac770ae2094b",
      "title": "what can i expect from australia",
      "blogList": [],
      "description1": "Quidem excepturi ut vero. Aut eos omnis. Pariatur et rem. Ea eaque ducimus. Dicta excepturi quia.\n \rAut quia autem provident magnam necessitatibus in. Dolores nobis aut facilis iure. Vel soluta totam hic eaque ut ipsam ut qui ab. Quae et voluptatem exercitationem eos vel ea.\n \rLaborum qui ut. Consectetur ullam est alias hic sit ducimus et porro. Qui ut nostrum necessitatibus minima. Aut delectus sapiente. Placeat aut assumenda quae.\n \rEligendi cupiditate sunt architecto odit inventore suscipit quia. Iure tenetur ut. Rerum ea illo laudantium. Veniam ut aspernatur qui et.",
      "description2": "Ullam architecto dolorum distinctio nobis fugiat sit soluta. Veritatis eius ut voluptatem. Velit vel sed. Odit unde dolores similique eos.\n \rQuia ut fugiat aut in explicabo. Dolores voluptatem magnam voluptatem quos quidem possimus est. Quaerat autem repudiandae adipisci. Assumenda animi deleniti dolorum eveniet eum officia vero.\n \rTemporibus repellendus tempore eos laboriosam atque inventore. Eum in tempore qui cum aut natus. Eaque necessitatibus suscipit quis maxime aut inventore et. Nobis doloribus et laudantium et quae corporis tempore voluptatum facere. Hic odit ipsam repellendus tempore aut assumenda fugiat.\n \rIure repellendus repellat aut consequatur ut dolore dolores iusto. Molestias nam illo similique in et minima tenetur iusto consequatur. Nostrum optio quia necessitatibus sint laudantium.",
      "categories": ["camping", "restaurants"],
      "hearts": 0,
      "comments": 0,
      "time": 1666560266016
    },
    {
      "idDestination": 3,
      "id": "4132a190-df1f-48e6-ac83-2924e124d0e0",
      "title": "what can i expect from peru",
      "blogList": [],
      "description1": "Laborum ea ut non omnis iure est ex hic occaecati. Ut officiis dolorem consectetur deleniti optio voluptate aut. Est laboriosam beatae sit ut.\n \rDolor fugiat vel laborum odit sapiente soluta maiores. Enim quos incidunt. Ad omnis qui cum molestiae animi. Inventore ut sint veritatis nostrum sequi sed amet dolorem impedit. Ut vel suscipit qui maiores. Cumque omnis et quae quam aliquid.\n \rSoluta et nostrum odio doloribus rerum. Debitis incidunt sed molestias. Quo rerum eum aut harum omnis excepturi numquam. Fugit consectetur laborum hic ad consequatur ipsum incidunt. Blanditiis autem repellat nihil sint laboriosam. Et sint voluptas autem accusantium soluta eligendi laudantium rerum expedita.\n \rQuod dicta nemo rerum quam ullam fugiat laboriosam. Minus et et quia. Quod libero voluptas sunt et excepturi explicabo esse sed.",
      "description2": "Autem dolores dolores id. Dolor qui officia alias. Ad suscipit ipsa est aliquid error sed rem ullam molestiae. Nesciunt id quos qui veniam dolorem quo quos deleniti.\n \rEum ut vitae distinctio dolor qui tempore odit vel. Possimus ut totam voluptas. Et eos aspernatur sint non possimus consectetur voluptatem sequi. Sit asperiores placeat consectetur laborum cum autem qui rerum qui.\n \rAut qui omnis et fugiat aliquam et similique. Alias dolores eum ea eveniet rerum nisi facilis ut. Ullam asperiores tempore similique mollitia. Dolor blanditiis illum corporis sed animi nemo consequatur. Qui possimus fugit harum ipsa vitae sit reiciendis repellendus.\n \rMinus ut tenetur ea et voluptatem. Et et officia odio delectus molestiae asperiores impedit accusamus voluptatem. Sed facere officia repellat ut voluptatem. Explicabo et vel perferendis dolorem aut iste. Voluptatem ipsam porro iure illum omnis sequi.",
      "categories": ["low budget"],
      "hearts": 0,
      "comments": 0,
      "time": 1666560430339
    },
    {
      "idDestination": 4,
      "id": "a5c4ea9c-a419-4580-a001-2ff616c41c52",
      "title": "what can i expect from brazil",
      "blogList": [],
      "description1": "Eius autem autem est autem voluptas occaecati. Consequuntur velit qui magnam ducimus exercitationem. Voluptas voluptas ut voluptatum quidem. Voluptatum blanditiis quia voluptatem. Suscipit quo ad voluptas est molestiae possimus consequatur quia.\n \rDeleniti voluptas at voluptatem dolore cupiditate atque et fuga enim. Qui voluptas rem molestiae sed. Dolor iusto consequatur iste est sit voluptatem. Labore dolor in dolorem. Error officiis iste inventore vel repellat. Vel voluptatibus omnis ullam consequatur sunt.\n \rVoluptatibus amet aut saepe velit. Non hic ratione perferendis eius consequatur mollitia omnis minima. Beatae corporis velit et dolor. Et quia ut commodi repellendus expedita rem asperiores et ad.\n \rEa cupiditate nam alias. Ducimus odio quia nihil. Optio in vel at reprehenderit suscipit qui et excepturi et. Pariatur doloremque et. Consectetur et velit nesciunt id non tenetur. Et laboriosam qui totam quas similique voluptatem.",
      "description2": "Et ad omnis laborum. Quas aut saepe adipisci temporibus ab. Non vitae consectetur at totam sequi. Similique aut totam et. Qui aut optio voluptate voluptatem. Voluptatem maxime et cupiditate necessitatibus voluptatibus.\n \rDoloremque perferendis qui quia voluptas nam tenetur. Ut reiciendis non modi itaque veritatis. Voluptas amet officia. Quas non voluptatem velit. Dolores tenetur earum.\n \rSapiente laborum odit aut quis inventore at perspiciatis. Molestiae reiciendis doloribus dignissimos cum alias nihil soluta reiciendis. Aut voluptatem earum quia consequuntur vitae libero. Eum id praesentium necessitatibus eos tempora tempore.\n \rNon quidem necessitatibus. Aut et quo quibusdam. Eum aperiam vero laboriosam ut rerum qui reprehenderit ea. Molestias sunt ut ut dolorem. Temporibus et nisi illo harum repellendus quisquam est iure est. Excepturi quaerat rerum quo fuga repellendus optio eos unde.",
      "categories": ["beaches", "photography"],
      "hearts": 0,
      "comments": 0,
      "time": 1666560601997
    },
    {
      "idDestination": 5,
      "id": "d6e2f41d-4ba9-4e0d-8ede-466552e2b81c",
      "title": "what can i expect from united kingdom",
      "blogList": [],
      "description1": "Perspiciatis amet rerum earum dolores molestiae corporis. Quo optio qui. Vitae voluptatem aut a. Inventore doloremque numquam quia corporis odit reiciendis unde nam laboriosam. Porro officia blanditiis accusantium veritatis assumenda assumenda et.\n \rEum qui maxime voluptatibus laboriosam tenetur ratione minus architecto neque. Ut dolor dicta officiis consequatur et dicta et. Et aut et mollitia itaque beatae eum blanditiis voluptas quod.\n \rTotam pariatur consectetur ex quo vel. Reiciendis eveniet perferendis dignissimos perferendis culpa a. Qui veritatis velit doloribus qui nesciunt.\n \rEarum nostrum debitis placeat sed. Cum id culpa maiores. Cupiditate aperiam quam asperiores ab illo laborum ipsum incidunt et. Consequatur ut quaerat tempore sunt pariatur maxime aspernatur rerum. Consequuntur quia sit sint eos aut blanditiis inventore enim soluta. Tempora vero nesciunt maiores sit molestiae doloribus libero.",
      "description2": "Aut ratione aperiam ab unde quis reiciendis et ex voluptatibus. Sint sit aut. Officiis aut sed qui omnis.\n \rQuos in blanditiis id sit dolorem facilis. Quo eos recusandae officia dicta eaque quam. Dolore animi veritatis cupiditate porro impedit atque maiores. Omnis neque dolor. Tenetur velit voluptatum alias cum culpa ea in illum. Et autem vel reiciendis repellendus.\n \rTemporibus eum et. Earum saepe laudantium numquam nulla eum in nesciunt. Corporis voluptas harum et facere dicta provident. Aspernatur et esse natus temporibus eligendi.\n \rEa alias labore. Similique quis magnam tempore aut quod ad nesciunt mollitia. Dolores quia perferendis eligendi accusantium ab laboriosam est ut. Vel eius sed eum animi neque illo laudantium placeat. Expedita quis eos nesciunt officiis quis voluptatem.",
      "categories": ["flights", "guides"],
      "hearts": 0,
      "comments": 0,
      "time": 1666560733674
    },
    {
      "idDestination": 6,
      "id": "9307c5e7-352b-465d-92cf-54480aff5325",
      "title": "what can i expect from italy",
      "blogList": [],
      "description1": "Et voluptatem debitis libero culpa est nostrum voluptates. Voluptatem quas et. Magnam facilis corrupti aliquam et ullam ad temporibus. Esse provident qui consequatur rerum ea nam necessitatibus vitae.\n \rQui ex esse est. Voluptas quibusdam minus ut numquam. Quod provident iste a omnis aliquid. Et voluptatem sed et consectetur aut dolorem.\n \rQui sed veniam qui et voluptatem et officiis unde. Hic voluptas commodi ut. Omnis architecto molestiae. Numquam doloremque consequatur dolorem quis et. Et aut aut molestiae omnis culpa labore natus sed doloremque. Qui sapiente et repudiandae nesciunt perspiciatis qui nisi reprehenderit nisi.\n \rRerum nihil dolorum magnam. Pariatur pariatur quidem et. Velit amet quo laborum quia sit dolore. Qui vel iure molestiae ab pariatur quis voluptas sunt quae. Omnis aliquam qui qui officiis qui amet ea earum.",
      "description2": "Vero ad numquam aut placeat non quia corporis voluptates. Quibusdam velit qui voluptatibus facilis quia. Minima quo qui id et. Est deleniti libero error voluptatum beatae esse voluptatum ea fuga.\n \rAutem molestiae nam cupiditate eveniet cupiditate reprehenderit. Ipsa saepe corrupti sed est nihil magnam quibusdam corrupti. Explicabo magnam sit quod. Facilis sit non dignissimos.\n \rAut perferendis culpa facilis illo repellendus repudiandae. Aperiam enim sunt enim deleniti facere. Quisquam et enim sunt eaque voluptate est.\n \rSed qui ut harum est totam quas voluptate. Dolores deleniti architecto numquam inventore voluptas qui qui. Culpa omnis commodi itaque minus magnam corrupti omnis. Et est tempore quo ut aut aut. Soluta fuga aut dolore impedit. Amet illo velit enim et commodi.",
      "categories": ["flights", "shopping"],
      "hearts": 0,
      "comments": 0,
      "time": 1666560796293
    },
    {
      "idDestination": 7,
      "id": "8ee48995-1a17-4e7a-94fc-4b35f46cd7b3",
      "title": "what can i expect from india",
      "blogList": [],
      "description1": "Deleniti nam et doloremque nesciunt dignissimos et ut non neque. Dolor dignissimos modi in et neque. Non nihil et vel eligendi voluptates commodi tempora reiciendis. Ratione provident velit et. Doloremque voluptatem excepturi in voluptas. Corrupti deserunt officia est blanditiis.\n \rMinus animi minus quidem odit dignissimos. Numquam consequuntur unde suscipit. Facere quia minima a et recusandae.\n \rDolor est omnis velit. Porro molestias rerum similique totam in. Hic quisquam quo explicabo reiciendis exercitationem est ea modi.\n \rNisi doloremque doloremque consectetur rerum laboriosam. Qui necessitatibus ipsa. Quisquam deserunt qui. Rerum eius saepe qui autem iure cupiditate occaecati. Dolores quo blanditiis ipsam qui facilis laudantium quasi aut quaerat. Quia et quibusdam accusantium magnam facilis earum consequatur dicta.",
      "description2": "Provident consectetur vero deserunt nihil velit. Aperiam ratione tempore distinctio. Est omnis aut molestiae est autem tempora. Ipsam ut corrupti voluptas nihil incidunt non.\n \rAt neque enim in et in aut odit dignissimos qui. Vero veritatis eligendi animi debitis. Quibusdam quas repellendus magnam cumque et in dicta. Nostrum et qui harum.\n \rEt alias corporis deserunt quas voluptas. Ad et ad nihil. Vel provident ipsum officiis culpa sint consequatur. Doloremque quis esse et asperiores sunt. Blanditiis nulla est maxime.\n \rNam reprehenderit cumque necessitatibus repellendus fugit quo. Vel sapiente dolorem occaecati. Non vero veniam sunt adipisci voluptatem nisi nemo ab excepturi. Sapiente facilis explicabo quia voluptatem beatae aut rerum sunt aspernatur. Qui doloremque aut iure quidem quo quia ut enim in. Laborum occaecati suscipit id quisquam expedita repellat.",
      "categories": ["flights", "beaches"],
      "hearts": 0,
      "comments": 0,
      "time": 1666560942110
    },
    {
      "idDestination": 8,
      "id": "5e5cf93f-bd84-4221-ba47-6c7a7b8987d7",
      "title": "what can i expect from greece",
      "blogList": [],
      "description1": "Autem voluptatum rerum quidem quo eos quod. Est id libero fuga quibusdam itaque in consectetur exercitationem autem. Eaque praesentium quas deserunt. Dolores corporis rerum sit sed. Rem placeat aut est unde facere fuga hic voluptatem.\n \rQui est cumque earum harum reiciendis. Laudantium modi ut. Qui sed itaque enim beatae cupiditate qui ut quibusdam. Omnis mollitia velit ut ullam qui et quis ipsa.\n \rFacilis adipisci ratione rerum non voluptatem totam aliquam. Autem modi voluptatibus voluptatem voluptatibus sed et praesentium commodi ab. Nisi architecto tempora harum amet. Ipsum magni quia. Doloremque iste nobis sed quisquam et. Consequatur ad possimus et quia aut sunt ut.\n \rEt accusamus debitis eius sunt ut aut. Qui ab quaerat sed odio ducimus vitae voluptatem doloremque ut. Omnis facere voluptatem fuga voluptatum consequatur sint. Qui quos maiores accusamus et aspernatur amet ullam quia laboriosam. Error delectus ducimus soluta esse.",
      "description2": "Quo ratione ut. Molestiae voluptatum quas. Blanditiis voluptatem inventore rerum esse commodi ut molestiae qui dolorem. Sed a est. Necessitatibus facilis voluptatum aperiam veritatis aut omnis quas dolore.\n \rUllam incidunt repellendus deleniti eveniet fugiat libero commodi. Ut commodi aut. Accusamus alias aut consectetur voluptas. Officia necessitatibus doloribus. Tempora perspiciatis nihil soluta molestiae porro. Sint explicabo magnam sed minima consequuntur.\n \rBeatae et vel voluptas et assumenda ut dolorum mollitia. Optio sed non. Sint cupiditate asperiores vel quasi recusandae et.\n \rEt nesciunt corporis molestiae. Ex esse autem mollitia consequatur mollitia. Quas odit aliquid maxime ullam beatae quidem iusto culpa.",
      "categories": ["flights", "guides"],
      "hearts": 0,
      "comments": 0,
      "time": 1666561006954
    },
    {
      "idDestination": 9,
      "id": "5fc3bff0-ecf6-4266-8ff5-85eb40a8c6d7",
      "title": "what can i expect from france",
      "blogList": [],
      "description1": "Vero et incidunt vero vero aut. Sapiente voluptatem quo. Et nisi ab architecto.\n \rEst optio laboriosam quam odio reprehenderit rem est totam fugiat. Eaque nihil fuga. Distinctio repellendus perferendis alias minus praesentium est eveniet laborum. Consequatur rerum assumenda. Et vel sed eum atque voluptas alias. Sequi vitae in.\n \rAnimi commodi quaerat rerum cupiditate et ad temporibus. Quibusdam inventore id ipsa. Deleniti harum saepe corporis delectus quidem veritatis ipsam. Totam nulla voluptas autem est minus natus et. Reiciendis dolores dolorum.\n \rEt eveniet illum laborum quisquam quidem omnis ab animi dolor. Ducimus et rerum accusamus. Sed aut mollitia aut repudiandae.",
      "description2": "Sit id maiores ea est in architecto eos vero sed. Qui quia quia laudantium dolore ex sint. Facilis qui et incidunt enim nihil animi itaque non voluptatem. Quo est dolorem provident tenetur. Ducimus tempore fuga voluptatem.\n \rDolor sit aut et. Nostrum eaque fugiat perferendis accusantium sed officiis totam praesentium. Ipsa impedit veniam omnis sunt omnis optio. Beatae aut voluptatem doloribus porro asperiores dolor inventore vel.\n \rQuae quos molestias eius natus itaque quia voluptas. Animi commodi expedita omnis ex totam hic tempora excepturi dolorum. Et voluptas repellendus itaque perspiciatis quos. Aperiam labore nesciunt modi voluptatum. Ipsam aliquam et similique voluptas rerum similique optio quam. Voluptas eius quidem qui.\n \rLabore aliquam laborum. Minus soluta et velit alias id consequatur. Maiores et ullam doloremque omnis harum. Quisquam tenetur iure nostrum suscipit error.",
      "categories": ["flights", "guides"],
      "hearts": 0,
      "comments": 0,
      "time": 1666561080305
    }
  ],

  "comment-list": [
    {
      "idDestination": 1,
      "id": "5e832d34-ce2d-4462-a25a-e6167fb3eca1",
      "avatar": "https://secure.gravatar.com/avatar/35abd0f841f006c1533f3d113ff172a9?s=96&d=mm&r=g",
      "author": "Khang Nguyen",
      "content": "Expedita dolorem excepturi mollitia ut autem quibusdam vitae necessitatibus. Repellendus adipisci adipisci quasi quia expedita veniam ut officiis reprehenderit. Consequuntur adipisci consequatur modi ut deleniti ut. Nihil dolor quae ducimus omnis. Et consequatur et veniam.",
      "time": 1666554133234
    },
    {
      "idDestination": 1,
      "id": "5e832d34-ce2d-4462-a25a-e6167fb3eca2",
      "avatar": "https://secure.gravatar.com/avatar/35abd0f841f006c1533f3d113ff172a9?s=96&d=mm&r=g",
      "author": "Khang Nguyen",
      "content": "Expedita dolorem excepturi mollitia ut autem quibusdam vitae necessitatibus. Repellendus adipisci adipisci quasi quia expedita veniam ut officiis reprehenderit. Consequuntur adipisci consequatur modi ut deleniti ut. Nihil dolor quae ducimus omnis. Et consequatur et veniam.",
      "time": 1666554133234
    },
    {
      "idDestination": 2,
      "id": "566e9b01-67a2-4c33-8371-f88e64a11ae9",
      "avatar": "https://secure.gravatar.com/avatar/35abd0f841f006c1533f3d113ff172a9?s=96&d=mm&r=g",
      "author": "Khang Nguyen",
      "content": "Est a ullam commodi enim et provident eum aut consequatur. Libero eum est blanditiis a ratione. Eius rerum totam eum ratione. Assumenda qui nihil.",
      "time": 1666560266016
    },
    {
      "idDestination": 3,
      "id": "d215fcb8-1dba-4543-b0c1-699583829a70",
      "avatar": "https://secure.gravatar.com/avatar/35abd0f841f006c1533f3d113ff172a9?s=96&d=mm&r=g",
      "author": "Khang Nguyen",
      "content": "Qui dolore repudiandae illum dicta in expedita. Quia et nesciunt iste. Et doloribus culpa in dolorem illum nesciunt omnis.",
      "time": 1666560430339
    },
    {
      "idDestination": 4,
      "id": "9e5b48c2-77bb-4ace-8709-f98aa999f073",
      "avatar": "https://secure.gravatar.com/avatar/35abd0f841f006c1533f3d113ff172a9?s=96&d=mm&r=g",
      "author": "Khang Nguyen",
      "content": "Eaque nihil in qui doloremque blanditiis rerum. Blanditiis ut aperiam nulla. Voluptates voluptatem voluptatibus optio vero asperiores et similique.",
      "time": 1666560601997
    },
    {
      "idDestination": 5,
      "id": "6dcbc315-1809-4f94-927c-faf352688ec3",
      "avatar": "https://secure.gravatar.com/avatar/35abd0f841f006c1533f3d113ff172a9?s=96&d=mm&r=g",
      "author": "Khang Nguyen",
      "content": "Reprehenderit cum eum ea asperiores doloribus deleniti accusantium ut a. Laboriosam animi blanditiis quo eos. Expedita nemo eligendi nihil. Temporibus dignissimos assumenda. Quam neque voluptas nulla aut eius velit est.",
      "time": 1666560733674
    },
    {
      "idDestination": 6,
      "id": "925d71e8-153f-44d1-9915-c0337be82470",
      "avatar": "https://secure.gravatar.com/avatar/35abd0f841f006c1533f3d113ff172a9?s=96&d=mm&r=g",
      "author": "Khang Nguyen",
      "content": "Et quas officia sint non rem mollitia. Quia iste quibusdam laboriosam aut. Neque sed aliquam qui.",
      "time": 1666560796293
    },
    {
      "idDestination": 7,
      "id": "8a86e561-9163-4db1-b794-63496d6d60df",
      "avatar": "https://secure.gravatar.com/avatar/35abd0f841f006c1533f3d113ff172a9?s=96&d=mm&r=g",
      "author": "Khang Nguyen",
      "content": "Sit sit ipsa eveniet est. Hic quam quas tempore iusto quae dolores est molestiae. Quidem sint reprehenderit qui provident. Inventore aut et et possimus tempore incidunt vitae.",
      "time": 1666560942110
    },
    {
      "idDestination": 8,
      "id": "db310cc9-4970-4b10-98e4-286df44b0a4b",
      "avatar": "https://secure.gravatar.com/avatar/35abd0f841f006c1533f3d113ff172a9?s=96&d=mm&r=g",
      "author": "Khang Nguyen",
      "content": "Eos ut tempore perferendis. Alias vel nulla eius sed dignissimos voluptatem ipsam. Et velit magni. Voluptatum sed sequi repellendus natus.",
      "time": 1666561006954
    },
    {
      "idDestination": 9,
      "id": "04a7e9d9-fcff-4c03-8ded-ba490c210c1c",
      "avatar": "https://secure.gravatar.com/avatar/35abd0f841f006c1533f3d113ff172a9?s=96&d=mm&r=g",
      "author": "Khang Nguyen",
      "content": "Est voluptates vel nisi hic. Enim quia corrupti. Odio ea culpa quasi perspiciatis veritatis porro atque expedita. Vitae reprehenderit vero qui eos sunt et eum. Qui quisquam aliquid aliquid rerum ad ea quisquam. Repellendus odio minus rerum quasi et nihil.",
      "time": 1666561080305
    }
  ],

  "products": [
    {
      "id": 1,
      "image": "https://backpacktraveler.qodeinteractive.com/wp-content/uploads/2018/08/produc-1t-1.png",
      "rating": 4,
      "price": 24.0,
      "name": "501 places",
      "description": "Eam tale eros civibus ad. Vel cu habemus iudicabit referrentur, cu est autem omnesque. Dolorum accusamus at vel, duo putent accommodare ei. In veritus tacimates convenire mea, eam quas falli eripuit et. Ne graece audiam sea, fabellas urbanitas assueverit sea.",
      "additionalInfor": [{ "weight": "1kg" }, { "dimensions": "15 × 15 × 15 cm" }],
      "review": [
        {
          "avatar": "https://secure.gravatar.com/avatar/97e966e9c7bd27f3fb9356449be8fc8d?s=120&d=mm&r=g",
          "idReview": "1",
          "rate": 5,
          "createdAt": 1666554133234,
          "updatedAt": 1666554133234,
          "reviewName": "Khang Nguyen",
          "reviewContent": "Lorem ipsum dolor sit amet consectetur adipisicing elit. Corporis voluptate saepe earum eum perferendis doloribus esse nobis cumque commodi natus non facere, vel porro ullam nesciunt cupiditate voluptatibus deleniti ad"
        }
      ]
    },

    {
      "id": 2,
      "image": "https://backpacktraveler.qodeinteractive.com/wp-content/uploads/2018/08/produc8.png",
      "rating": 5,
      "price": 22.0,
      "name": "ALMOST FEARLESS",
      "description": "Eam tale eros civibus ad. Vel cu habemus iudicabit referrentur, cu est autem omnesque. Dolorum accusamus at vel, duo putent accommodare ei. In veritus tacimates convenire mea, eam quas falli eripuit et. Ne graece audiam sea, fabellas urbanitas assueverit sea.",
      "additionalInfor": [{ "weight": "1kg" }, { "dimensions": "15 × 15 × 15 cm" }],
      "review": [
        {
          "avatar": "https://secure.gravatar.com/avatar/97e966e9c7bd27f3fb9356449be8fc8d?s=120&d=mm&r=g",
          "idReview": "1",
          "rate": 5,
          "createdAt": 1666554133234,
          "updatedAt": 1666554133234,
          "reviewName": "Khang Nguyen",
          "reviewContent": "Lorem ipsum dolor sit amet consectetur adipisicing elit. Corporis voluptate saepe earum eum perferendis doloribus esse nobis cumque commodi natus non facere, vel porro ullam nesciunt cupiditate voluptatibus deleniti ad"
        }
      ]
    },

    {
      "id": 3,
      "image": "https://backpacktraveler.qodeinteractive.com/wp-content/uploads/2018/08/produc4.png",
      "rating": 4,
      "price": 33.0,
      "name": "FRANCE IN 6 DAYS",
      "description": "Eam tale eros civibus ad. Vel cu habemus iudicabit referrentur, cu est autem omnesque. Dolorum accusamus at vel, duo putent accommodare ei. In veritus tacimates convenire mea, eam quas falli eripuit et. Ne graece audiam sea, fabellas urbanitas assueverit sea.",
      "additionalInfor": [{ "weight": "1kg" }, { "dimensions": "15 × 15 × 15 cm" }],
      "review": [
        {
          "avatar": "https://secure.gravatar.com/avatar/2da1f2301ed41ebc2880d6863f7995ef?s=120&d=mm&r=g",
          "idReview": "1",
          "rate": 5,
          "createdAt": 1666554133234,
          "updatedAt": 1666554133234,
          "reviewName": "Olivia",
          "reviewContent": "Donec accumsan lorem leo, eu vehicula odio congue sit amet. Donec interdum eget est ac aliquam. Duis viverra vehicula odio, vitae mattis urna gravida nec. Nulla malesuada elit eget tortor tempor ultrices. Donec venenatis cursus risus. Duis vel suscipit orci, eget lacinia justo. Etiam nec neque in arcu elementum mollis."
        }
      ]
    },

    {
      "id": 4,
      "image": "https://backpacktraveler.qodeinteractive.com/wp-content/uploads/2018/08/produc3.png",
      "rating": 5,
      "price": 31.0,
      "name": "GREECE",
      "description": "Eam tale eros civibus ad. Vel cu habemus iudicabit referrentur, cu est autem omnesque. Dolorum accusamus at vel, duo putent accommodare ei. In veritus tacimates convenire mea, eam quas falli eripuit et. Ne graece audiam sea, fabellas urbanitas assueverit sea.",
      "additionalInfor": [{ "weight": "1kg" }, { "dimensions": "15 × 15 × 15 cm" }],
      "review": [
        {
          "avatar": "https://secure.gravatar.com/avatar/35abd0f841f006c1533f3d113ff172a9?s=96&d=mm&r=g",
          "idReview": "1",
          "rate": 5,
          "createdAt": 1666554133234,
          "updatedAt": 1666554133234,
          "reviewName": "Khang Nguyen",
          "reviewContent": "Lorem ipsum dolor sit amet consectetur adipisicing elit. Corporis voluptate saepe earum eum perferendis doloribus esse nobis cumque commodi natus non facere, vel porro ullam nesciunt cupiditate voluptatibus deleniti ad"
        },

        {
          "avatar": "https://secure.gravatar.com/avatar/97e966e9c7bd27f3fb9356449be8fc8d?s=120&d=mm&r=g",
          "idReview": "2",
          "rate": 5,
          "createdAt": 1666554133234,
          "updatedAt": 1666554133234,
          "reviewName": "Flower",
          "reviewContent": "Cras vestibulum aliquam vulputate. Nam a erat blandit, laoreet ex eleifend, bibendum augue. Maecenas est sem, vulputate at massa a, dignissim pulvinar orci"
        }
      ]
    },

    {
      "id": 5,
      "image": "https://backpacktraveler.qodeinteractive.com/wp-content/uploads/2018/08/produc5.png",
      "rating": 3,
      "price": 29.0,
      "name": "WANDERING EDUCATORS",
      "description": "Eam tale eros civibus ad. Vel cu habemus iudicabit referrentur, cu est autem omnesque. Dolorum accusamus at vel, duo putent accommodare ei. In veritus tacimates convenire mea, eam quas falli eripuit et. Ne graece audiam sea, fabellas urbanitas assueverit sea.",
      "additionalInfor": [{ "weight": "1kg" }, { "dimensions": "15 × 15 × 15 cm" }],
      "review": [
        {
          "avatar": "https://secure.gravatar.com/avatar/2da1f2301ed41ebc2880d6863f7995ef?s=120&d=mm&r=g",
          "idReview": "1",
          "rate": 5,
          "createdAt": 1666554133234,
          "updatedAt": 1666554133234,
          "reviewName": "Olivia",
          "reviewContent": "Donec accumsan lorem leo, eu vehicula odio congue sit amet. Donec interdum eget est ac aliquam. Duis viverra vehicula odio, vitae mattis urna gravida nec. Nulla malesuada elit eget tortor tempor ultrices. Donec venenatis cursus risus. Duis vel suscipit orci, eget lacinia justo. Etiam nec neque in arcu elementum mollis."
        }
      ]
    },

    {
      "id": 6,
      "image": "https://backpacktraveler.qodeinteractive.com/wp-content/uploads/2018/08/produc6.png",
      "rating": 5,
      "price": 28.0,
      "name": "LIFE CRUISER",
      "description": "Eam tale eros civibus ad. Vel cu habemus iudicabit referrentur, cu est autem omnesque. Dolorum accusamus at vel, duo putent accommodare ei. In veritus tacimates convenire mea, eam quas falli eripuit et. Ne graece audiam sea, fabellas urbanitas assueverit sea.",
      "additionalInfor": [{ "weight": "1kg" }, { "dimensions": "15 × 15 × 15 cm" }],
      "review": []
    },

    {
      "id": 7,
      "image": "https://backpacktraveler.qodeinteractive.com/wp-content/uploads/2018/08/produc7.png",
      "rating": 4,
      "price": 27.0,
      "name": "NEW YORK",
      "description": "Eam tale eros civibus ad. Vel cu habemus iudicabit referrentur, cu est autem omnesque. Dolorum accusamus at vel, duo putent accommodare ei. In veritus tacimates convenire mea, eam quas falli eripuit et. Ne graece audiam sea, fabellas urbanitas assueverit sea.",
      "additionalInfor": [{ "weight": "1kg" }, { "dimensions": "15 × 15 × 15 cm" }],
      "review": [
        {
          "avatar": "https://secure.gravatar.com/avatar/35abd0f841f006c1533f3d113ff172a9?s=96&d=mm&r=g",
          "idReview": "1",
          "rate": 5,
          "createdAt": 1666554133234,
          "updatedAt": 1666554133234,
          "reviewName": "Khang Nguyen",
          "reviewContent": "Lorem ipsum dolor sit amet consectetur adipisicing elit. Corporis voluptate saepe earum eum perferendis doloribus esse nobis cumque commodi natus non facere, vel porro ullam nesciunt cupiditate voluptatibus deleniti ad"
        },

        {
          "avatar": "https://secure.gravatar.com/avatar/97e966e9c7bd27f3fb9356449be8fc8d?s=120&d=mm&r=g",
          "idReview": "2",
          "rate": 5,
          "createdAt": 1666554133234,
          "updatedAt": 1666554133234,
          "reviewName": "Flower",
          "reviewContent": "Cras vestibulum aliquam vulputate. Nam a erat blandit, laoreet ex eleifend, bibendum augue. Maecenas est sem, vulputate at massa a, dignissim pulvinar orci"
        }
      ]
    },

    {
      "id": 8,
      "image": "https://backpacktraveler.qodeinteractive.com/wp-content/uploads/2018/08/product-11.png",
      "rating": 5,
      "price": 35.0,
      "name": "TRAVEL",
      "description": "Eam tale eros civibus ad. Vel cu habemus iudicabit referrentur, cu est autem omnesque. Dolorum accusamus at vel, duo putent accommodare ei. In veritus tacimates convenire mea, eam quas falli eripuit et. Ne graece audiam sea, fabellas urbanitas assueverit sea.",
      "additionalInfor": [{ "weight": "1kg" }, { "dimensions": "15 × 15 × 15 cm" }],
      "review": [
        {
          "avatar": "https://secure.gravatar.com/avatar/e518cf671dd6e12907d6be828d0acfee?s=120&d=mm&r=g",
          "idReview": "1",
          "rate": 5,
          "createdAt": 1666554133234,
          "updatedAt": 1666554133234,
          "reviewName": "Nicole ",
          "reviewContent": "Cras vestibulum aliquam vulputate. Nam a erat blandit, laoreet ex eleifend, bibendum augue. Maecenas est sem, vulputate at massa a, dignissim pulvinar orci"
        }
      ]
    },

    {
      "id": 9,
      "image": "https://backpacktraveler.qodeinteractive.com/wp-content/uploads/2018/08/produc2t.png",
      "rating": 5,
      "price": 32.0,
      "name": "YOMADIC BEACHES",
      "description": "Eam tale eros civibus ad. Vel cu habemus iudicabit referrentur, cu est autem omnesque. Dolorum accusamus at vel, duo putent accommodare ei. In veritus tacimates convenire mea, eam quas falli eripuit et. Ne graece audiam sea, fabellas urbanitas assueverit sea.",
      "additionalInfor": [{ "weight": "1kg" }, { "dimensions": "15 × 15 × 15 cm" }],
      "review": []
    }
  ]
}
